{"users":[{"id":90151259.70138405,"firstName":"Lorem consequat irure minim","lastName":"in ea laborum","email":"labore do laborum"},{"id":35072582.652849905,"firstName":"quis id est","lastName":"sed incididunt anim do quis","email":"mollit amet ad"},{"id":918773.7594322744,"firstName":"veniam","lastName":"nostrud","email":"mollit in sunt sit"},{"id":37638611.61508237,"firstName":"qui officia fugiat","lastName":"laboris magna cillum ipsum","email":"consequat ad"},{"id":29267751.176070284,"firstName":"ea dolore ut","lastName":"non incididunt do exercitation ut","email":"Lorem Duis do"}]}